CHANGELOG
LICENSE
MANIFEST.in
README.txt
setup.py
binio/__init__.py
binio/types.py
binio/types_builder.py
binio.egg-info/PKG-INFO
binio.egg-info/SOURCES.txt
binio.egg-info/dependency_links.txt
binio.egg-info/top_level.txt